Queue/__init__.py
Queue/exceptions/__init__.py
Queue/exceptions/exceptions.py
Queue/functions/__init__.py
Queue/functions/function01.py
Queue/functions/function02.py
Queue/functions/function03.py
Queue/functions/functions.py
Queue/scripts/__init__.py
Queue/scripts/script01.py
queus-0.0.3.dist-info/METADATA
queus-0.0.3.dist-info/WHEEL
queus-0.0.3.dist-info/top_level.txt
queus-0.0.3.dist-info/RECORD
